{
  "settings": {
    "d": 64,
    "n_facts": 832,
    "n_attempts": 11,
    "input_vocab_size": 128,
    "output_vocab_size": 64,
    "d_ff": 64,
    "seed": 42,
    "metric": "best_guess_accuracy",
    "model": "RandomUpModel2",
    "n_epochs": 5000,
    "lr": 0.01,
    "patience": 100
  },
  "results": [
    {
      "n_facts": 832,
      "attempt": 0,
      "init_seed": 0,
      "best_guess_accuracy": 0.7067307829856873,
      "epochs_run": 3647
    },
    {
      "n_facts": 832,
      "attempt": 1,
      "init_seed": 1,
      "best_guess_accuracy": 0.817307710647583,
      "epochs_run": 5000
    },
    {
      "n_facts": 832,
      "attempt": 2,
      "init_seed": 2,
      "best_guess_accuracy": 0.8762019276618958,
      "epochs_run": 5000
    },
    {
      "n_facts": 832,
      "attempt": 3,
      "init_seed": 3,
      "best_guess_accuracy": 0.7475962042808533,
      "epochs_run": 3731
    },
    {
      "n_facts": 832,
      "attempt": 4,
      "init_seed": 4,
      "best_guess_accuracy": 0.8353365659713745,
      "epochs_run": 5000
    },
    {
      "n_facts": 832,
      "attempt": 5,
      "init_seed": 5,
      "best_guess_accuracy": 0.8233173489570618,
      "epochs_run": 5000
    },
    {
      "n_facts": 832,
      "attempt": 6,
      "init_seed": 6,
      "best_guess_accuracy": 0.7788462042808533,
      "epochs_run": 4071
    },
    {
      "n_facts": 832,
      "attempt": 7,
      "init_seed": 7,
      "best_guess_accuracy": 0.8004807829856873,
      "epochs_run": 5000
    },
    {
      "n_facts": 832,
      "attempt": 8,
      "init_seed": 8,
      "best_guess_accuracy": 0.7740384936332703,
      "epochs_run": 4149
    },
    {
      "n_facts": 832,
      "attempt": 9,
      "init_seed": 9,
      "best_guess_accuracy": 0.806490421295166,
      "epochs_run": 5000
    },
    {
      "n_facts": 832,
      "attempt": 10,
      "init_seed": 10,
      "best_guess_accuracy": 0.7367788553237915,
      "epochs_run": 3815
    }
  ]
}